vickie/__init__.py
vickie/base.py
vickie/exceptions.py
vickie/main.py
vickie/schema.py
vickie/types/__init__.py
vickie/types/composite.py
vickie/types/misc.py
vickie/types/number.py
vickie/types/string.py
vickie/utils.py
vickie/validators/__init__.py
vickie/validators/alphabet.py
vickie/validators/crypto.py
vickie/validators/email.py
vickie/validators/finance.py
vickie/validators/net.py
vickie/validators/phone.py
vickie/validators/product.py
vickie/validators/url.py
vickie-0.3.0.dist-info/LICENSE
vickie-0.3.0.dist-info/METADATA
vickie-0.3.0.dist-info/WHEEL
vickie-0.3.0.dist-info/RECORD
