Metadata-Version: 2.1
Name: vickie
Version: 0.3.0
Summary: THe All-in-One Validator.
Author: walidsa3d
Requires-Python: >=3.10,<4.0
Classifier: Programming Language :: Python :: 3
Classifier: Programming Language :: Python :: 3.10
Classifier: Programming Language :: Python :: 3.11
Classifier: Programming Language :: Python :: 3.12
Classifier: Programming Language :: Python :: 3.13
Requires-Dist: click (>=8.1.3,<9.0.0)
Requires-Dist: dnspython (>=2.6.1,<3.0.0)
Requires-Dist: phonenumbers (>=8.13.43,<9.0.0)
